setup.py
sftpmgr.py
sftpmgr.egg-info/PKG-INFO
sftpmgr.egg-info/SOURCES.txt
sftpmgr.egg-info/dependency_links.txt
sftpmgr.egg-info/entry_points.txt
sftpmgr.egg-info/requires.txt
sftpmgr.egg-info/top_level.txt