Metadata-Version: 1.0
Name: sftpmgr
Version: 0.1
Summary: SFTP Stack Manager CLI Tool
Home-page: https://github.com/ethanmcc/sftpmgr
Author: Ethan McCreadie
Author-email: ethanmcc@gmail.com
License: UNKNOWN
Platform: UNKNOWN
